quark_plugin_mis/__init__.py
quark_plugin_mis/classical_mis_solver.py
quark_plugin_mis/mis_graph_provider.py
quark_plugin_mis-0.1.8.dist-info/licenses/LICENSE
quark_plugin_mis-0.1.8.dist-info/licenses/NOTICE
quark_plugin_mis-0.1.8.dist-info/METADATA
quark_plugin_mis-0.1.8.dist-info/WHEEL
quark_plugin_mis-0.1.8.dist-info/top_level.txt
quark_plugin_mis-0.1.8.dist-info/RECORD
