Metadata-Version: 2.4
Name: QUARK-plugin-mis
Version: 0.1.8
Summary: Quark plugin providing problem generation and mapping modules for the maximum independent set problem
Author-email: Philipp Ross <philipp.ross@bmw.de>, Marvin Erdmann <marvin.erdmann@bmw.de>, Andre Luckow <andre.luckow@bmwgroup.com>, Greshma Shaji <greshma.shaji@bmwgroup.com>, Florian Kiwit <florian.kiwit@bmw.de>, Benjamin Decker <benjamin.decker@bmw.de>
License-Expression: Apache-2.0
Project-URL: Homepage, https://github.com/QUARK-framework/QUARK-plugin-mis
Classifier: Programming Language :: Python :: 3
Classifier: Operating System :: OS Independent
Requires-Python: >=3.12
License-File: LICENSE
License-File: NOTICE
Requires-Dist: dwave-networkx>=0.8.18
Requires-Dist: pulser>=1.5.4
Requires-Dist: quark-framework>=0.1.9
Dynamic: license-file
